README
setup.py
pyrouette/__init__.py
pyrouette.egg-info/PKG-INFO
pyrouette.egg-info/SOURCES.txt
pyrouette.egg-info/dependency_links.txt
pyrouette.egg-info/top_level.txt
pyrouette/cartpole/__init__.py
pyrouette/cmac/__init__.py
pyrouette/cmac/core.py
pyrouette/cmac/fast.c
pyrouette/dtw/__init__.py
pyrouette/dtw/fast.c
pyrouette/gridworld/__init__.py
pyrouette/gridworld/boyan.py
pyrouette/gridworld/chainwalk.py
pyrouette/gridworld/gridworld.py
pyrouette/gridworld/gridworld8.py
pyrouette/gridworld/gridworldgui.py
pyrouette/gridworld/gridworldlake.py
pyrouette/gridworld/markovdp.py
pyrouette/gridworld/mimic.py
pyrouette/gridworld/vergence.py
pyrouette/isomap/__init__.py
pyrouette/lspi/__init__.py
pyrouette/lspi/lspi.py
pyrouette/lspi/lstdq.py
pyrouette/lspi/trackknown.py
pyrouette/mds/__init__.py
pyrouette/mds/mds.py
pyrouette/pca/__init__.py
pyrouette/pca/fast_pca.c
pyrouette/pca/fast_pca.pyx
pyrouette/pca/pca.py
pyrouette/td/__init__.py
pyrouette/td/sutton.py
pyrouette/utils/__init__.py
pyrouette/utils/axline.py
pyrouette/utils/pickle_utils.py
pyrouette/utils/plot_utils.py
pyrouette/utils/utils.py