Metadata-Version: 1.1
Name: pyrouette
Version: 0.6.0
Summary: A pythonic machine learning library
Home-page: http://pyrouette.org
Author: Jeremy Stober
Author-email: stober@gmail.com
License: BSD
Keywords: machine learning algorithms cmac
Platform: UNKNOWN
Classifier: Programming Language :: Python
Classifier: License :: OSI Approved :: BSD License
Classifier: Development Status :: 4 - Beta
